range_key_dict/__init__.py
range_key_dict/range_key_dict.py
range_key_dict_2-2.0.0.dist-info/LICENSE
range_key_dict_2-2.0.0.dist-info/METADATA
range_key_dict_2-2.0.0.dist-info/WHEEL
range_key_dict_2-2.0.0.dist-info/top_level.txt
range_key_dict_2-2.0.0.dist-info/RECORD
