Metadata-Version: 2.1
Name: range-key-dict-2
Version: 2.0.0
Summary: A modern dict implementation supporting range-based keys with O(log M) lookups
Author-email: Matthew Odos <odosmatthews@example.com>
Maintainer-email: Matthew Odos <odosmatthews@example.com>
License: MIT
Project-URL: Homepage, https://github.com/odosmatthews/range-key-dict-2
Project-URL: Bug Tracker, https://github.com/odosmatthews/range-key-dict-2/issues
Project-URL: Source Code, https://github.com/odosmatthews/range-key-dict-2
Project-URL: Original Project, https://github.com/albertmenglongli/range-key-dict
Keywords: range,dict,interval,mapping,data-structure
Classifier: Development Status :: 4 - Beta
Classifier: Intended Audience :: Developers
Classifier: License :: OSI Approved :: MIT License
Classifier: Programming Language :: Python :: 3
Classifier: Programming Language :: Python :: 3.8
Classifier: Programming Language :: Python :: 3.9
Classifier: Programming Language :: Python :: 3.10
Classifier: Programming Language :: Python :: 3.11
Classifier: Programming Language :: Python :: 3.12
Classifier: Programming Language :: Python :: 3.13
Classifier: Topic :: Software Development :: Libraries :: Python Modules
Classifier: Typing :: Typed
Requires-Python: >=3.8
License-File: LICENSE
Provides-Extra: dev
Requires-Dist: pytest>=7.0.0; extra == "dev"
Requires-Dist: pytest-cov>=4.0.0; extra == "dev"
Requires-Dist: black>=23.0.0; extra == "dev"
Requires-Dist: isort>=5.12.0; extra == "dev"
Requires-Dist: ruff>=0.1.0; extra == "dev"
Requires-Dist: mypy>=1.0.0; extra == "dev"
Requires-Dist: pre-commit>=3.0.0; extra == "dev"
